LineTextParser/__init__.py
LineTextParser-2.0.1.dist-info/METADATA
LineTextParser-2.0.1.dist-info/WHEEL
LineTextParser-2.0.1.dist-info/top_level.txt
LineTextParser-2.0.1.dist-info/RECORD
